cyclic_agent/__init__.py
cyclic_agent/executor.py
cyclic_agent/state.py
cyclic_agent-0.1.0.dist-info/LICENSE
cyclic_agent-0.1.0.dist-info/METADATA
cyclic_agent-0.1.0.dist-info/WHEEL
cyclic_agent-0.1.0.dist-info/RECORD
