Metadata-Version: 2.1
Name: cyclic-agent
Version: 0.1.0
Summary: Build LLM powered, fully autonomous agents.
Author: xingjianll
Author-email: 4396kevinliu@gmail.com
Requires-Python: >=3.12,<4.0
Classifier: Programming Language :: Python :: 3
Classifier: Programming Language :: Python :: 3.12
Requires-Dist: overrides (>=7.7.0,<8.0.0)
Requires-Dist: pydantic (>=2.8.2,<3.0.0)
